{
  "insufficient_balance": "You don't have enough balance!",
  "player_not_found": "Player not found!",
  "invalid_amount": "Invalid amount!",
  "cannot_pay_yourself": "You cannot pay yourself!",
  "payment_sent": "Payment sent successfully!",
  "payment_received": "You received a payment!",
  "balance_set": "Balance set successfully!",
  "balance_added": "Balance added successfully!",
  "usage_money": "Usage: /money [nick]",
  "usage_pay": "Usage: /money pay <nick> <amount>",
  "usage_set": "Usage: /money set <nick> <amount>",
  "usage_give": "Usage: /money give <nick> <amount>",
  "no_permission": "You don't have permission to use this command!",
  "balance_of": "Balance of {player}",
  "top_10_richest": "Top 10 Richest",
  "top_separator": "=========================================",
  "top_no_players": "No players found in ranking.",
  "top_position": "{position} {player}: {balance}",
  "balance_set_to": "Balance of {player} set to {amount}",
  "balance_added_to": "Added {amount} to {player}. New balance: {balance}",
  "money_received": "You received {amount}.",
  "balance_set_notification": "Your balance has been set to {amount}.",
  "plugin_loaded": "EconomySystem loaded successfully!",
  "ore_rewards": "Ore rewards: {status}",
  "wood_rewards": "Wood rewards: {status}",
  "ores_configured": "Configured ores: {count} items",
  "api_available": "Public API available: com.economy.api.EconomyAPI",
  "loading_balances": "Loading balance data...",
  "error_loading_balances": "ERROR LOADING BALANCE FILE",
  "error_saving_balances": "ERROR SAVING BALANCE FILE",
  "balances_saved": "Economy data saved",
  "initial_balance_given": "Initial balance of ${amount} given to player: {player}",
  "enabled": "Enabled",
  "disabled": "Disabled",
  "shop_item_added": "Item added to shop! Unique ID: {uniqueid}, Item: {itemid}, Quantity: {quantity}, Sell Price: {pricesell}, Buy Price: {pricebuy}",
  "shop_item_removed": "Item removed from shop! Unique ID: {uniqueid}",
  "shop_item_not_found": "Item not found! Unique ID: {uniqueid}",
  "invalid_arguments": "Invalid arguments!",
  "shop_item_bought": "You bought {quantity}x {item} for {price}!",
  "shop_item_sold": "You sold {quantity}x {item} for {price}!",
  "shop_insufficient_balance": "You don't have enough balance! Required: {amount}",
  "shop_insufficient_items": "You don't have enough items! Required: {quantity}x {item}",
  "shop_confirm_buy": "Do you want to buy {quantity}x {item} for {price}?",
  "shop_confirm_sell": "Do you want to sell {quantity}x {item} for {price}?",
  "shop_quantity_label": "Quantity:",
  "shop_button_confirm": "Confirm",
  "shop_button_cancel": "Cancel",
  "playershop_owner_sold": "You sold {quantity}x {item} to {player} for {money}",
  "playershop_owner_bought": "You bought {quantity}x {item} from {player} for {money}",
  "playershop_insufficient_stock": "Insufficient stock!",
  "shop_empty": "No items in shop",
  "shops_player_shop": "{player}'s Shop",
  "shops_items_count": "items",
  "error_inventory_add": "Error adding item to inventory. Money refunded.",
  "error_inventory_remove": "Error removing item from inventory.",
  "error_item_info": "Error getting item information: {error}",
  "error_item_add": "Error adding item: {error}",
  "error_item_remove": "Error removing item: {error}",
  "item_not_found": "Item not found! ID: {itemid}",
  "shop_title": "Admin Shop - The Economy",
  "shops_title": "You are viewing player shops.",
  "playershop_title": "This shop belongs to player {player}.",
  "shop_price_buy_label": "B: ",
  "shop_price_sell_label": "S: ",
  "shop_price_separator": " / ",
  "playershop_stock_label": "Stock: ",
  "myshop_confirm_remove": "Do you want to remove item {item} (ID: {uniqueid}) from your shop?",
  "playershop_tooltip_click_remove": "Click to remove item",
  "myshop_usage_tab": "Usage: /myshop tab <create|remove> <name>",
  "gui_shop_manager_add_console": "Add Console",
  "gui_shop_manager_add_console_title": "Add Console Command",
  "gui_shop_npc_add_title": "Add Shop NPC",
  "gui_shop_npc_add_name": "NPC Name:",
  "gui_shop_npc_add_model": "NPC Model:",
  "gui_shop_manager_console_display_name": "Name:",
  "gui_shop_manager_console_command": "Command:",
  "gui_shop_manager_console_icon": "Icon (Hotbar Item)",
  "chat_shop_console_added": "Console command added! Name: {name}, Command: {command}, Price: {pricebuy}",
  "chat_shop_console_bought": "You bought {quantity}x {item} for {price}!",
  "gui_shop_tooltip_console_command": "Console Command",
  "chat_shop_manager_console_display_name_empty": "Name cannot be empty!",
  "chat_shop_manager_console_command_empty": "Command cannot be empty!",
  "chat_shop_manager_console_icon_empty": "Select an icon from hotbar!",
  "chat_error_console_add": "Error adding console command: {error}",
  "chat_shop_rename_player_usage": "Usage: /shop renameplayershop <nick> <name>",
  "chat_shop_rename_player_success": "Shop renamed successfully! Player: {player}, New name: {name}",
  "chat_shop_rename_player_error": "Error renaming player shop.",
  "npc_interaction_open_shop": "Press F to open the shop"
}

